num2cyrillic.py
num2cyrillic-1.0.0.dist-info/METADATA
num2cyrillic-1.0.0.dist-info/RECORD
num2cyrillic-1.0.0.dist-info/WHEEL
num2cyrillic-1.0.0.dist-info/top_level.txt
