Metadata-Version: 2.1
Name: num2cyrillic
Version: 1.0.0
Summary: Python class for converting numbers into Bulgarian cyrillic words
Home-page: https://github.com/ClaimCompass/num2cyrillic
Author: claimcompass.eu
Author-email: info@claimcompass.eu
License: LGPLv3
Download-URL: https://github.com/ClaimCompass/num2cyrillic
Platform: UNKNOWN
Classifier: Programming Language :: Python :: 3
Classifier: License :: OSI Approved :: GNU Lesser General Public License v3 (LGPLv3)
Classifier: Operating System :: OS Independent
